{
  "db_name": "PostgreSQL",
  "query": "\n            INSERT INTO auth.email_account (email, password_hash, user_id) \n            VALUES ($1, $2, $3) ON CONFLICT (email) \n            DO NOTHING \n            RETURNING *",
  "describe": {
    "columns": [
      {
        "ordinal": 0,
        "name": "id",
        "type_info": "Uuid"
      },
      {
        "ordinal": 1,
        "name": "email",
        "type_info": "Varchar"
      },
      {
        "ordinal": 2,
        "name": "password_hash",
        "type_info": "Text"
      },
      {
        "ordinal": 3,
        "name": "user_id",
        "type_info": "Uuid"
      },
      {
        "ordinal": 4,
        "name": "banned_at",
        "type_info": "Timestamp"
      }
    ],
    "parameters": {
      "Left": [
        "Varchar",
        "Text",
        "Uuid"
      ]
    },
    "nullable": [
      false,
      false,
      false,
      false,
      true
    ]
  },
  "hash": "aa9ee748e4f3347f2fac920ae99e0dccd7e7a3948a3170e646f4993b68ae3e8b"
}
